cplearn/__init__.py
cplearn/coremap/__init__.py
cplearn/coremap/anchored_map.py
cplearn/coremap/coremap.py
cplearn/coremap/coremap_algo.py
cplearn/coremap/coremap_graph_utils.py
cplearn/coremap/coremap_utils.py
cplearn/corespect/__init__.py
cplearn/corespect/cav.py
cplearn/corespect/cluster_core.py
cplearn/corespect/clustering_algo.py
cplearn/corespect/corespect.py
cplearn/corespect/louvain_setup.py
cplearn/corespect/propagate.py
cplearn/corespect/ranking.py
cplearn/utils/__init__.py
cplearn/utils/densify.py
cplearn/utils/graph_utils.py
cplearn/utils/louvain_setup.py
cplearn/utils/processing.py
cplearn/utils/umap_spectral.py
cplearn/visualizer/__init__.py
cplearn/visualizer/visualizer.py
cplearn/visualizer/viz_utils.py
cplearn-0.1.1.dist-info/licenses/LICENSE
cplearn-0.1.1.dist-info/METADATA
cplearn-0.1.1.dist-info/WHEEL
cplearn-0.1.1.dist-info/top_level.txt
cplearn-0.1.1.dist-info/RECORD
