Metadata-Version: 2.4
Name: cplearn
Version: 0.1.1
Summary: Enhancing unsupervised learning with geometry-density interactions via decomposition of data into geometric core-periphery layers and subsequent clustering
Author: Chandra Sekhar Mukherjee
Author-email: Chandra Sekhar Mukherjee <chandrasekhar.mukherjee07@gmail.com>, "Joonyoung (Aaron) Bae" <joonyoungbae.aaron@gmail.com>
License-Expression: GPL-3.0-or-later
Requires-Python: <=3.12.10,>=3.0
License-File: LICENSE
Requires-Dist: hdbscan>=0.8.40
Requires-Dist: hnswlib>=0.8.0
Requires-Dist: networkx>=3.1
Requires-Dist: numba>=0.57.1
Requires-Dist: numpy>=1.24.3
Requires-Dist: pandas>=2.0.3
Requires-Dist: scikit-learn>=1.6.1
Requires-Dist: plotly<7.0,>=6.0
Requires-Dist: flatbuffers<25.0,>=24.0
Requires-Dist: umap-learn<1.0.0,>=0.5.9.post2
Dynamic: license-file
